pydglab_ws/__init__.py
pydglab_ws/client/__init__.py
pydglab_ws/client/base.py
pydglab_ws/client/connect.py
pydglab_ws/client/local.py
pydglab_ws/client/ws.py
pydglab_ws/enums.py
pydglab_ws/exceptions.py
pydglab_ws/models.py
pydglab_ws/server/__init__.py
pydglab_ws/server/server.py
pydglab_ws/typing.py
pydglab_ws/utils.py
pydglab_ws-1.1.0.dist-info/LICENSE
pydglab_ws-1.1.0.dist-info/METADATA
pydglab_ws-1.1.0.dist-info/WHEEL
pydglab_ws-1.1.0.dist-info/RECORD
