Metadata-Version: 2.1
Name: pydglab-ws
Version: 1.1.0
Summary: 一个通过 WebSocket 控制郊狼 DG-Lab 的 Python 库
Home-page: https://pydglab-ws.readthedocs.io
Keywords: dg-lab,dg-lab-v3,websocket,library,os-independent
Author: Ljzd-PRO
Author-email: ljzd@office.ljzd-pro.asia
Requires-Python: >=3.8
Classifier: Development Status :: 5 - Production/Stable
Classifier: License :: OSI Approved :: BSD License
Classifier: Operating System :: OS Independent
Classifier: Programming Language :: Python :: 3
Classifier: Programming Language :: Python :: 3.8
Classifier: Programming Language :: Python :: 3.9
Classifier: Programming Language :: Python :: 3.10
Classifier: Programming Language :: Python :: 3.11
Classifier: Programming Language :: Python :: 3.12
Classifier: Topic :: Software Development :: Libraries :: Python Modules
Requires-Dist: pydantic (>=2.7.1,<3.0.0)
Requires-Dist: websockets (>=12.0,<13.0)
Project-URL: Documentation, https://pydglab-ws.readthedocs.io
Project-URL: Repository, https://github.com/Ljzd-PRO/PyDGLab-WS
